dataset/__init__.py
outputs/__init__.py
pretrained_models/__init__.py
torchblocks/__init__.py
torchblocks/callback/__init__.py
torchblocks/callback/adversarial.py
torchblocks/callback/early_stopping.py
torchblocks/callback/ema.py
torchblocks/callback/file_writer.py
torchblocks/callback/logger.py
torchblocks/callback/model_checkpoint.py
torchblocks/callback/progressbar.py
torchblocks/data/Vocabulary.py
torchblocks/data/__init__.py
torchblocks/data/embedding.py
torchblocks/data/tokenizer.py
torchblocks/losses/__init__.py
torchblocks/losses/focal_loss.py
torchblocks/losses/hard_mining.py
torchblocks/losses/kd_loss.py
torchblocks/losses/kl_divergence.py
torchblocks/losses/label_smoothing.py
torchblocks/losses/span_loss.py
torchblocks/losses/symmetric_ce.py
torchblocks/losses/triplet_loss.py
torchblocks/metrics/__init__.py
torchblocks/metrics/base.py
torchblocks/metrics/classification.py
torchblocks/metrics/regression.py
torchblocks/metrics/sequence_labeling.py
torchblocks/metrics/utils.py
torchblocks/models/__init__.py
torchblocks/models/bases/__init__.py
torchblocks/models/bases/configuration_base.py
torchblocks/models/bases/model_base.py
torchblocks/models/nn/__init__.py
torchblocks/models/nn/bert_for_attr.py
torchblocks/models/nn/bert_for_multilabel.py
torchblocks/models/nn/bert_for_ner.py
torchblocks/models/nn/bert_for_relation.py
torchblocks/models/nn/bert_for_siamese.py
torchblocks/models/nn/bert_for_triple.py
torchblocks/models/nn/bert_with_mdp.py
torchblocks/models/nn/lstm_crf.py
torchblocks/models/transformer/__init__.py
torchblocks/models/transformer/configuration_albert.py
torchblocks/models/transformer/configuration_nezha.py
torchblocks/models/transformer/convert_albert_original_tf_checkpoint_to_pytorch.py
torchblocks/models/transformer/modeling_albert.py
torchblocks/models/transformer/modeling_bert_for_theseus.py
torchblocks/models/transformer/modeling_nezha.py
torchblocks/models/transformer/utils.py
torchblocks/optims/__init__.py
torchblocks_chen-1.0.1.10.dist-info/LICENSE
torchblocks_chen-1.0.1.10.dist-info/METADATA
torchblocks_chen-1.0.1.10.dist-info/WHEEL
torchblocks_chen-1.0.1.10.dist-info/top_level.txt
torchblocks_chen-1.0.1.10.dist-info/RECORD
